activitypub/__init__.py
activitypub/apps.py
activitypub/contexts.py
activitypub/decorators.py
activitypub/exceptions.py
activitypub/factories.py
activitypub/handlers.py
activitypub/parsers.py
activitypub/permissions.py
activitypub/processors.py
activitypub/renderers.py
activitypub/resolvers.py
activitypub/settings.py
activitypub/signals.py
activitypub/signatures.py
activitypub/tasks.py
activitypub/admin/__init__.py
activitypub/admin/actions.py
activitypub/admin/admins.py
activitypub/admin/filters.py
activitypub/migrations/0001_initial.py
activitypub/migrations/__init__.py
activitypub/models/__init__.py
activitypub/models/ap.py
activitypub/models/as2.py
activitypub/models/base.py
activitypub/models/collections.py
activitypub/models/fields.py
activitypub/models/integrity_proofs.py
activitypub/models/languages.py
activitypub/models/linked_data.py
activitypub/models/schemadotorg.py
activitypub/models/sec.py
activitypub/serializers/__init__.py
activitypub/serializers/as2.py
activitypub/serializers/base.py
activitypub/serializers/fields.py
activitypub/serializers/linked_data.py
activitypub/serializers/nodeinfo.py
activitypub/tests/__init__.py
activitypub/tests/base.py
activitypub/tests/conftest.py
activitypub/tests/settings.py
activitypub/tests/test_models.py
activitypub/tests/test_serializers.py
activitypub/tests/test_tasks.py
activitypub/tests/test_views.py
activitypub/tests/urls.py
activitypub/views/__init__.py
activitypub/views/activitystreams.py
activitypub/views/discovery.py
activitypub/views/linked_data.py
django_activitypub_toolkit-0.1.5.dist-info/licenses/LICENSE
django_activitypub_toolkit-0.1.5.dist-info/METADATA
django_activitypub_toolkit-0.1.5.dist-info/WHEEL
django_activitypub_toolkit-0.1.5.dist-info/top_level.txt
django_activitypub_toolkit-0.1.5.dist-info/RECORD
