Metadata-Version: 2.4
Name: django-activitypub-toolkit
Version: 0.1.5
Summary: Django pluggable application to ActivityPub servers
Author-email: Raphael Lullis <raphael@mushroomlabs.com>
License: BSD-3-Clause
Keywords: django,activitypub
Classifier: Environment :: Web Environment
Classifier: Framework :: Django
Classifier: Framework :: Django :: 4.2
Classifier: Framework :: Django :: 5.0
Classifier: Framework :: Django :: 5.1
Classifier: Intended Audience :: Developers
Classifier: License :: OSI Approved :: BSD License
Classifier: Programming Language :: Python :: 3
Classifier: Programming Language :: Python :: 3.9
Classifier: Programming Language :: Python :: 3.10
Classifier: Programming Language :: Python :: 3.11
Classifier: Programming Language :: Python :: 3.12
Classifier: Programming Language :: Python :: 3.13
Classifier: Programming Language :: Python :: 3.14
Classifier: Topic :: Internet :: WWW/HTTP
Requires-Python: <4,>=3.9
License-File: LICENSE
Requires-Dist: django>=4.2.26
Requires-Dist: django-model-utils>=4.2
Requires-Dist: djangorestframework>=3.13
Requires-Dist: celery>=5.4
Requires-Dist: pyld>=2.0.4
Requires-Dist: rdflib>=7.0.0
Requires-Dist: requests-http-message-signatures>=0.3.1
Requires-Dist: django-celery-beat>=2.7.0
Requires-Dist: python-ulid<4.0.0,>=3.0.0
Provides-Extra: dev
Requires-Dist: factory-boy; extra == "dev"
Requires-Dist: pytest; extra == "dev"
Requires-Dist: pytest-django; extra == "dev"
Requires-Dist: pytest-env; extra == "dev"
Requires-Dist: pytest-socket; extra == "dev"
Requires-Dist: httpretty; extra == "dev"
Provides-Extra: docs
Requires-Dist: mkdocs; extra == "docs"
Requires-Dist: mkdocs-material; extra == "docs"
Requires-Dist: mkdocs-macros-plugin; extra == "docs"
Requires-Dist: mkdocstrings[python]; extra == "docs"
Dynamic: license-file
